github_secret_syncer/__init__.py
github_secret_syncer-0.0.10.dist-info/LICENSE
github_secret_syncer-0.0.10.dist-info/METADATA
github_secret_syncer-0.0.10.dist-info/WHEEL
github_secret_syncer-0.0.10.dist-info/top_level.txt
github_secret_syncer-0.0.10.dist-info/RECORD
